virustotal_python/__init__.py
virustotal_python/virustotal.py
virustotal_python-1.1.1.dist-info/METADATA
virustotal_python-1.1.1.dist-info/WHEEL
virustotal_python-1.1.1.dist-info/licenses/LICENSE
virustotal_python-1.1.1.dist-info/RECORD
