Metadata-Version: 2.4
Name: virustotal-python
Version: 1.1.1
Summary: A Python library to interact with the public VirusTotal v3 and v2 APIs.
Project-URL: Homepage, https://github.com/dbrennand/virustotal-python
Project-URL: Repository, https://github.com/dbrennand/virustotal-python
Author: dbrennand
License-Expression: MIT
License-File: LICENSE
Keywords: Library,Public API,VirusTotal,Wrapper,v2,v3
Classifier: Programming Language :: Python :: 3
Classifier: Programming Language :: Python :: 3.7
Classifier: Programming Language :: Python :: 3.8
Classifier: Programming Language :: Python :: 3.9
Classifier: Programming Language :: Python :: 3.10
Classifier: Programming Language :: Python :: 3.11
Classifier: Programming Language :: Python :: 3.12
Classifier: Programming Language :: Python :: 3.13
Requires-Python: >=3.12
Requires-Dist: requests>=2.32.5
Provides-Extra: socks
Requires-Dist: pysocks>=1.7.1; extra == 'socks'
